pybottrader/__init__.py
pybottrader/indicators.py
pybottrader/portfolios.py
pybottrader/strategies.py
pybottrader/traders.py
pybottrader/datastreamers/__init__.py
pybottrader/datastreamers/yfinance.py
pybottrader-0.0.6.dist-info/LICENSE
pybottrader-0.0.6.dist-info/METADATA
pybottrader-0.0.6.dist-info/WHEEL
pybottrader-0.0.6.dist-info/top_level.txt
pybottrader-0.0.6.dist-info/RECORD
