Metadata-Version: 2.1
Name: pybottrader
Version: 0.0.6
Summary: An experimental Python library to implement trading bots
License:                     GNU GENERAL PUBLIC LICENSE
Project-URL: Documentation, https://jailop.github.io/pybottrader/pybottrader.html
Project-URL: Repository, https://github.com/jailop/pybottrader
Keywords: trading,bots,finance
License-File: LICENSE
Requires-Dist: attrs
Requires-Dist: numpy
Requires-Dist: pandas
Requires-Dist: yfinance
Provides-Extra: dev
Requires-Dist: ipython; extra == "dev"
Requires-Dist: jupyter; extra == "dev"
Requires-Dist: jupyterlab; extra == "dev"
Requires-Dist: mypy; extra == "dev"
Requires-Dist: pandas-stubs; extra == "dev"
Requires-Dist: pdoc; extra == "dev"
Requires-Dist: pylint; extra == "dev"
Requires-Dist: pytest; extra == "dev"
Requires-Dist: black; extra == "dev"
Requires-Dist: sphinx; extra == "dev"
Requires-Dist: sphinx-rtd-theme; extra == "dev"
Requires-Dist: sphinx-autodoc-typehints; extra == "dev"
